<?xml version="1.0" encoding="utf-8"?>
<resources>
    <!-- App Names-->
    <string name="app.authenticator">身份验证器</string>
    <string name="app.calculator">计算机</string>
    <string name="app.clock">时钟</string>
    <string name="app.containers" comment="Do not actually translate this string, just write &quot;Graft&quot; as the translation">Graft虚拟机</string>
    <string name="app.disks">磁盘</string>
    <string name="app.files">文件</string>
    <string name="app.media">媒体库</string>
    <string name="app.music">音乐</string>
    <string name="app.notes">文本编辑器</string>
    <string name="app.notesmobile">笔记(移动端)</string>
    <string name="app.messages">信息</string>
    <string name="app.rootterminal">根用户终端</string>
    <string name="app.settings">设定</string>
    <string name="app.systemlogs">系统日志</string>
    <string name="app.taskmanager">任务管理器</string>
    <string name="app.terminal">终端</string>
    <string name="app.themedemo">主题演示</string>
    <string name="app.welcome">欢迎</string>
    <string name="app.help">帮助</string>
    <string name="app.web">网页浏览器</string>
    <!-- App Descriptions-->
    <string name="app.authenticator_description">双重验证</string>
    <string name="app.calculator_description">添加、删减、乘法和除法</string>
    <string name="app.clock_description">管理时间、闹钟、拦截器和世界时钟</string>
    <string name="app.containers_description">管理你的系统容器</string>
    <string name="app.disks_description">管理磁盘和分区</string>
    <string name="app.files_description">浏览文件和文件夹</string>
    <string name="app.media_description">浏览和观看照片和视频</string>
    <string name="app.music_description">收听本地音乐</string>
    <string name="app.notes_description">编辑本地文本文件</string>
    <string name="app.notesmobile_description">笔记(移动端)</string>
    <string name="app.messages_description">信息</string>
    <string name="app.rootterminal_description">以管理员形式打开终端</string>
    <string name="app.settings_description">调整系统设置</string>
    <string name="app.systemlogs_description">读取系统日志</string>
    <string name="app.taskmanager_description">管理当前正在运行的应用程序</string>
    <string name="app.terminal_description">访问命令行</string>
    <string name="app.themedemo_description">应用主题内部演示模式</string>
    <string name="app.welcome_description">欢迎应用程序</string>
    <string name="app.help_description">问答和帮助</string>
    <string name="app.web_description">浏览网络</string>
    <!-- Feature Not Implemented-->
    <string name="misc.featurenotimplemented_title">尚未实现的功能</string>
    <string name="misc.featurenotimplemented_value">这个功能在你建造的Pangolin版本并不适用，请前往dahliaOS.io查看更新</string>
    <!-- Quicksettings-->
    <string name="qs.quick_controls">快捷操作</string>
    <string name="qs.airplanemode">飞航模式</string>
    <string name="qs.autorotate">自动旋转</string>
    <string name="qs.bluetooth">蓝牙</string>
    <string name="qs.changelanguage" comment="Replace this with the name of the language you're translating to">中文</string>
    <string name="qs.dnd">勿扰模式</string>
    <string name="qs.flashlight">闪光灯</string>
    <string name="qs.invertcolors">颜色反转</string>
    <string name="qs.theme">主题</string>
    <string name="qs.wifi">Wi-Fi</string>
    <!-- Launcher-->
    <string name="launcher.search">搜索设备，应用程序和网页内容</string>
    <string name="launcher.categories.all"> 所有应用</string>
    <string name="launcher.categories.internet">互联网</string>
    <string name="launcher.categories.media">媒体库</string>
    <string name="launcher.categories.gaming">游戏</string>
    <string name="launcher.categories.development">开发</string>
    <string name="launcher.categories.office">Office</string>
    <string name="launcher.categories.system">系统</string>
    <!-- Settings Tabs-->
    <string name="settings.tabs.connections">连接</string>
    <string name="settings.tabs.sound">音量和声音</string>
    <string name="settings.tabs.display">显示</string>
    <string name="settings.tabs.customization">个性化</string>
    <string name="settings.tabs.applications">应用程序</string>
    <string name="settings.tabs.security">安全</string>
    <string name="settings.tabs.accounts">账户</string>
    <string name="settings.tabs.backup">备份</string>
    <string name="settings.tabs.devoptions">开发人员选项</string>
    <string name="settings.tabs.general">通用管理</string>
    <string name="settings.tabs.updates">更新</string>
    <string name="settings.tabs.about">关于此设备</string>
    <string name="settings.tabs.search">搜索设置...</string>
    <!-- Settings Description-->
    <string name="settings.tabs.connections.description">Wi-Fi，蓝牙和其他连接</string>
    <string name="settings.tabs.sound.description">声音，音量</string>
    <string name="settings.tabs.display.description">亮度，过滤蓝光</string>
    <string name="settings.tabs.customization.description">个性化dahliaOS的样式</string>
    <string name="settings.tabs.applications.description">管理应用程序和全选</string>
    <string name="settings.tabs.security.description">安全和隐私</string>
    <string name="settings.tabs.accounts.description">管理和添加账户</string>
    <string name="settings.tabs.backup.description">备份和回复</string>
    <string name="settings.tabs.devoptions.description">功能标志，高级选项</string>
    <string name="settings.tabs.general.description">语言，键盘，时钟</string>
    <string name="settings.tabs.updates.description">更新日志，更新，源码</string>
    <string name="settings.tabs.about.description">状态，软件信息</string>
    <!-- Settings Header-->
    <string name="settings.header.connections">连接</string>
    <string name="settings.header.sound">音效</string>
    <string name="settings.header.display">显示</string>
    <string name="settings.header.customization">个性化</string>
    <string name="settings.header.applications">应用程序</string>
    <string name="settings.header.security">安全</string>
    <string name="settings.header.accounts">账户</string>
    <string name="settings.header.backup">备份</string>
    <string name="settings.header.devoptions">开发人员选项</string>
    <string name="settings.header.general">通用管理</string>
    <string name="settings.header.updates">更新</string>
    <string name="settings.header.about">关于此设备</string>
    <!-- Settings Connections-->
    <string name="settings.connections.wifi_and_bluetooth">Wi-Fi 和蓝牙</string>
    <string name="settings.connections.enableWifi">启用 Wi-Fi</string>
    <string name="settings.connections.enableBluetooth">启用蓝牙</string>
    <!-- Settings Sound-->
    <string name="settings.sound.system_volume">系统音量</string>
    <string name="settings.sound.volume_levels">音量级别</string>
    <string name="settings.sound.output">输出</string>
    <string name="settings.sound.input">输入</string>
    <string name="settings.sound.system_volume_desc">调整系统音量级别</string>
    <string name="settings.sound.volume_levels_desc">调整单个应用程序的音量</string>
    <string name="settings.sound.output_desc">选择输出设备</string>
    <string name="settings.sound.input_desc">选择输入设备</string>
    <!-- Settings Display-->
    <string name="settings.display.screen">屏幕</string>
    <string name="settings.display.blue_light_filter">蓝光过滤器</string>
    <string name="settings.display.resolution">分辨率</string>
    <string name="settings.display.screen_desc">设置您的屏幕亮度</string>
    <string name="settings.display.blue_light_filter_desc">启用蓝色光滤器来保护您的眼镜</string>
    <string name="settings.display.resolution_desc">调整您的屏幕分辨率</string>
    <!-- Settings Customization-->
    <string name="settings.customization.accent_color">强调颜色</string>
    <string name="settings.customization.colored_titlebar">使用彩色标题栏</string>
    <string name="settings.customization.use_colored_titlebars">使用彩色标题栏</string>
    <string name="settings.customization.dark_mode">暗黑模式</string>
    <string name="settings.customization.enable_dark_mode">在桌面和所有应用程序打开暗黑模式</string>
    <string name="settings.customization.blur">模糊</string>
    <string name="settings.customization.enable_blur">在桌面启用模糊效果</string>
    <string name="settings.customization.taskbar">任务栏</string>
    <string name="settings.customization.enable_centered_taskbar">居中任务栏</string>
    <string name="settings.customization.opacity">不透明度</string>
    <string name="settings.customization.change_opacity">更改界面元素的不透明度</string>
    <string name="settings.customization.font">字体</string>
    <string name="settings.customization.choose_font">选择系统字体类别</string>
    <string name="settings.customization.desktop">桌面</string>
    <string name="settings.customization.choose_wallpaper_desc">选择桌面壁纸</string>
    <string name="settings.customization.choose_wallpaper_btn">选择壁纸</string>
    <!-- Settings General-->
    <string name="settings.general.language_and_region">语言和区域</string>
    <string name="settings.general.language">语言</string>
    <string name="settings.general.time">时间</string>
    <string name="settings.general.time_automatic_time">自动时间</string>
    <string name="settings.general.time_show_seconds">显示秒数</string>
    <string name="settings.general.time_enable_twentyfour_hours">启用24小时时间</string>
    <string name="settings.general.keyboard">键盘</string>
    <!-- Settings Updates-->
    <string name="settings.updates.software_updates">软件更新</string>
    <string name="settings.updates.enable_system_updates">启用系统更新</string>
    <string name="settings.updates.allow_unsigned_packages">允许未签名的软件包</string>
    <string name="settings.updates.update_package_url">更新软件包URL</string>
    <string name="settings.updates.button_update_system">更新系统</string>
    <string name="settings.updates.button_check_updates">检查更新</string>
    <!-- Settings About-->
    <string name="settings.about.version">版本</string>
    <string name="settings.about.kernel">内核</string>
    <string name="settings.about.pangolin_version">Pangolin 版本</string>
    <string name="settings.about.devoptions">开发人员选项</string>
    <string name="settings.about.enable_dev_options">启用开发人员选项</string>
</resources>
